agoradesk_py/__init__.py
agoradesk_py/agoradesk.py
agoradesk_py/py.typed
agoradesk_py-0.3.1.dist-info/LICENSE.md
agoradesk_py-0.3.1.dist-info/WHEEL
agoradesk_py-0.3.1.dist-info/METADATA
agoradesk_py-0.3.1.dist-info/RECORD
