Metadata-Version: 2.1
Name: agoradesk-py
Version: 0.3.1
Summary: Python Interface for Agoradesk.com and LocalMonero.co API
Home-page: https://codeberg.org/MarvinsCryptoTools/agoradesk_py
License: AGPL-3.0-or-later
Author: marvin8
Author-email: marvin8@tuta.io
Requires-Python: >=3.8,<4.0
Classifier: Intended Audience :: Developers
Classifier: License :: OSI Approved :: GNU Affero General Public License v3 or later (AGPLv3+)
Classifier: Operating System :: OS Independent
Classifier: Programming Language :: Python
Classifier: Programming Language :: Python :: 3
Classifier: Programming Language :: Python :: 3.10
Classifier: Programming Language :: Python :: 3.8
Classifier: Programming Language :: Python :: 3.9
Classifier: Topic :: Office/Business :: Financial
Requires-Dist: arrow (>=1.2.1,<2.0.0)
Requires-Dist: httpx (>=0.22.0,<0.23.0)
Project-URL: Bug Tracker, https://codeberg.org/MarvinsCryptoTools/agoradesk_py/issues
Project-URL: Changelog, https://codeberg.org/MarvinsCryptoTools/agoradesk_py/src/branch/main/CHANGELOG.md
Project-URL: Repository, https://codeberg.org/MarvinsCryptoTools/agoradesk_py
